pyvirtualmachine/__init__.py
pyvirtualmachine/gui.py
pyvirtualmachine/installer.py
pyvirtualmachine/vm_manager.py
pyvirtualmachine-1.0.0.dist-info/METADATA
pyvirtualmachine-1.0.0.dist-info/WHEEL
pyvirtualmachine-1.0.0.dist-info/entry_points.txt
pyvirtualmachine-1.0.0.dist-info/top_level.txt
pyvirtualmachine-1.0.0.dist-info/RECORD
